{
  "bets": [
    {
      "id": 1772995947058,
      "key": "401810776_sust_CLE",
      "gameId": "401810776",
      "team": "CLE",
      "opponent": "BOS",
      "matchup": "BOS @ CLE",
      "side": "SPREAD",
      "spread": 18.5,
      "signals": [
        "sust"
      ],
      "marketOdds": -102,
      "impliedP": 50.5,
      "estimatedP": 55,
      "kellyPct": 2.5,
      "kellyBet": 500,
      "book": "FanDuel",
      "timestamp": "2026-03-08T18:52:27.058Z",
      "outcome": null,
      "payout": null,
      "mode": "nba",
      "awayTeam": "BOS",
      "homeTeam": "CLE",
      "awayName": "Boston Celtics",
      "homeName": "Cleveland Cavaliers",
      "awayScore": 81,
      "homeScore": 58,
      "period": 3,
      "clock": "3:16",
      "periodLabel": "Q3",
      "sustLeader": "BOS",
      "sustMargin": 26,
      "betOnLeader": false,
      "currentMargin": -26,
      "cushion": -4.5,
      "sustScore": 27.5,
      "fragScore": -11.4,
      "sustGap": 38.9,
      "sustSignals": [
        "Low 3PT reliance (27%)"
      ],
      "fragSignals": [],
      "sustStats": {
        "fg": "33",
        "efg": "37",
        "threePt": "17",
        "twoPt": "55",
        "proc": 6.2,
        "star": 0,
        "scq": 5
      },
      "fragStats": {
        "fg": "46",
        "efg": "55",
        "threePt": "44",
        "twoPt": "40",
        "proc": 4.7,
        "star": 135,
        "scq": -20
      },
      "sustDetail": "CLE +26.6 vs BOS -7.4 (gap:34) | BOS 81-55 CLE | Q3 3:53 | FanDuel +18.5 (-102)",
      "strategies": {
        "g1_bigGap": false,
        "g2_procDriven": true,
        "g3_threePtDriven": false,
        "g4_starInvolved": true,
        "g5_betOnLeader": false,
        "g6_hasCushion": false,
        "g7_earlyGame": false,
        "g8_highProc": false,
        "g9_homeTeam": true,
        "g10_ncaa": false,
        "g11_bigMargin": true,
        "g12_oppCold3": false
      },
      "altGaps": {
        "v1_pureProc": 30,
        "v2_f1low": 35.7,
        "v3_f1high": 34.8,
        "v4_f3boost": 40,
        "v5_noStar": 34
      },
      "v7": {
        "aScq": -20.3,
        "hScq": 4.9,
        "aScore": -15.5,
        "hScore": 28.6,
        "gap": 44.1,
        "f5contrib": 10.1
      },
      "altStructural": {
        "v6_cushionBoost": 34,
        "v7_marginWeighted": 88.4,
        "v8_procDiffOnly": 15,
        "v10_timeDecay": 44.2
      },
      "espnOdds": {
        "provider": "Draft Kings",
        "spread": -1.5,
        "detail": "CLE -1.5",
        "awaySpread": "+1.5",
        "homeSpread": "-1.5",
        "awaySpreadOdds": "-112",
        "homeSpreadOdds": "-108",
        "awayML": "EVEN",
        "homeML": "-120",
        "openSpread": "-1.5"
      },
      "spreadHistory": [
        {
          "t": "2026-03-08T18:53:30.151Z",
          "spread": 18.5,
          "score": "81-55",
          "period": 3,
          "clock": "3:53"
        },
        {
          "t": "2026-03-08T18:53:31.266Z",
          "spread": 18.5,
          "score": "81-55",
          "period": 3,
          "clock": "3:53"
        },
        {
          "t": "2026-03-08T18:54:34.539Z",
          "spread": 18.5,
          "score": "81-58",
          "period": 3,
          "clock": "3:16"
        },
        {
          "t": "2026-03-08T18:54:36.010Z",
          "spread": 18.5,
          "score": "81-61",
          "period": 3,
          "clock": "2:59"
        },
        {
          "t": "2026-03-08T18:55:39.413Z",
          "spread": 16.5,
          "score": "86-61",
          "period": 3,
          "clock": "1:59"
        },
        {
          "t": "2026-03-08T18:55:40.667Z",
          "spread": 16.5,
          "score": "86-61",
          "period": 3,
          "clock": "1:59"
        },
        {
          "t": "2026-03-08T18:56:43.682Z",
          "spread": 18.5,
          "score": "86-61",
          "period": 3,
          "clock": "1:59"
        },
        {
          "t": "2026-03-08T18:56:43.684Z",
          "spread": 18.5,
          "score": "86-61",
          "period": 3,
          "clock": "1:59"
        },
        {
          "t": "2026-03-08T18:57:48.393Z",
          "spread": 18.5,
          "score": "86-63",
          "period": 3,
          "clock": "1:29"
        },
        {
          "t": "2026-03-08T18:57:48.639Z",
          "spread": 18.5,
          "score": "86-63",
          "period": 3,
          "clock": "1:29"
        },
        {
          "t": "2026-03-08T18:58:54.204Z",
          "spread": 14.5,
          "score": "86-66",
          "period": 3,
          "clock": "55.8"
        },
        {
          "t": "2026-03-08T18:58:54.205Z",
          "spread": 14.5,
          "score": "86-66",
          "period": 3,
          "clock": "55.8"
        },
        {
          "t": "2026-03-08T18:59:58.906Z",
          "spread": 13.5,
          "score": "86-69",
          "period": 3,
          "clock": "25.5"
        },
        {
          "t": "2026-03-08T18:59:58.919Z",
          "spread": 13.5,
          "score": "86-69",
          "period": 3,
          "clock": "25.5"
        },
        {
          "t": "2026-03-08T19:01:03.996Z",
          "spread": 12.5,
          "score": "86-69",
          "period": 3,
          "clock": "0.0"
        },
        {
          "t": "2026-03-08T19:01:04.000Z",
          "spread": 12.5,
          "score": "86-69",
          "period": 3,
          "clock": "0.0"
        },
        {
          "t": "2026-03-08T19:02:08.225Z",
          "spread": 12.5,
          "score": "86-69",
          "period": 3,
          "clock": "0.0"
        },
        {
          "t": "2026-03-08T19:02:08.492Z",
          "spread": 12.5,
          "score": "86-69",
          "period": 3,
          "clock": "0.0"
        },
        {
          "t": "2026-03-08T19:03:14.685Z",
          "spread": 12.5,
          "score": "86-69",
          "period": 3,
          "clock": "0.0"
        },
        {
          "t": "2026-03-08T19:03:14.704Z",
          "spread": 12.5,
          "score": "86-69",
          "period": 3,
          "clock": "0.0"
        },
        {
          "t": "2026-03-08T19:04:19.059Z",
          "spread": 12.5,
          "score": "86-71",
          "period": 4,
          "clock": "11:52"
        },
        {
          "t": "2026-03-08T19:04:19.077Z",
          "spread": 12.5,
          "score": "86-71",
          "period": 4,
          "clock": "11:52"
        },
        {
          "t": "2026-03-08T19:05:22.576Z",
          "spread": 11.5,
          "score": "88-71",
          "period": 4,
          "clock": "11:33"
        },
        {
          "t": "2026-03-08T19:05:22.820Z",
          "spread": 11.5,
          "score": "88-71",
          "period": 4,
          "clock": "11:33"
        },
        {
          "t": "2026-03-08T19:06:26.562Z",
          "spread": 12.5,
          "score": "91-74",
          "period": 4,
          "clock": "10:51"
        },
        {
          "t": "2026-03-08T19:06:26.563Z",
          "spread": 12.5,
          "score": "91-74",
          "period": 4,
          "clock": "10:51"
        },
        {
          "t": "2026-03-08T19:07:30.764Z",
          "spread": 13.5,
          "score": "91-75",
          "period": 4,
          "clock": "10:19"
        },
        {
          "t": "2026-03-08T19:07:30.779Z",
          "spread": 13.5,
          "score": "91-75",
          "period": 4,
          "clock": "10:19"
        },
        {
          "t": "2026-03-08T19:08:34.446Z",
          "spread": 11.5,
          "score": "91-76",
          "period": 4,
          "clock": "9:55"
        },
        {
          "t": "2026-03-08T19:08:34.566Z",
          "spread": 11.5,
          "score": "91-76",
          "period": 4,
          "clock": "9:55"
        },
        {
          "t": "2026-03-08T19:09:38.703Z",
          "spread": 11.5,
          "score": "91-78",
          "period": 4,
          "clock": "9:48"
        },
        {
          "t": "2026-03-08T19:09:38.715Z",
          "spread": 11.5,
          "score": "91-78",
          "period": 4,
          "clock": "9:48"
        },
        {
          "t": "2026-03-08T19:10:43.121Z",
          "spread": 11.5,
          "score": "91-78",
          "period": 4,
          "clock": "9:48"
        },
        {
          "t": "2026-03-08T19:10:43.446Z",
          "spread": 11.5,
          "score": "91-78",
          "period": 4,
          "clock": "9:48"
        },
        {
          "t": "2026-03-08T19:11:46.798Z",
          "spread": 11.5,
          "score": "91-78",
          "period": 4,
          "clock": "9:48"
        },
        {
          "t": "2026-03-08T19:11:47.848Z",
          "spread": 11.5,
          "score": "91-78",
          "period": 4,
          "clock": "9:48"
        }
      ],
      "alertSent": true
    },
    {
      "id": 1772995948235,
      "key": "401851548_sust_NAVY",
      "gameId": "401851548",
      "team": "NAVY",
      "opponent": "BU",
      "matchup": "BU @ NAVY",
      "side": "SPREAD",
      "spread": -6.5,
      "signals": [
        "sust"
      ],
      "marketOdds": -118,
      "impliedP": 54.1,
      "estimatedP": 55,
      "kellyPct": 2.5,
      "kellyBet": 500,
      "book": "FanDuel",
      "timestamp": "2026-03-08T18:52:28.235Z",
      "outcome": null,
      "payout": null,
      "mode": "ncaab",
      "awayTeam": "BU",
      "homeTeam": "NAVY",
      "awayName": "Boston University Terriers",
      "homeName": "Navy Midshipmen",
      "awayScore": 33,
      "homeScore": 33,
      "period": 1,
      "clock": "1:10",
      "periodLabel": "H1",
      "sustLeader": "TIE",
      "sustMargin": 0,
      "betOnLeader": false,
      "currentMargin": 0,
      "cushion": -6.5,
      "sustScore": 46.1,
      "fragScore": -16.1,
      "sustGap": 62.2,
      "sustSignals": [
        "Low 3PT reliance (9%)"
      ],
      "fragSignals": [
        "Star erupting (176% pace)"
      ],
      "sustStats": {
        "fg": "43",
        "efg": "45",
        "threePt": "17",
        "twoPt": "67",
        "proc": 6.9,
        "star": 83,
        "scq": 0
      },
      "fragStats": {
        "fg": "59",
        "efg": "68",
        "threePt": "44",
        "twoPt": "55",
        "proc": 4.7,
        "star": 176,
        "scq": 0
      },
      "sustDetail": "NAVY +46.1 vs BU -16.1 (gap:62.2) | BU 33-33 NAVY | H1 1:10 | FanDuel -6.5 (-118)",
      "strategies": {
        "g1_bigGap": true,
        "g2_procDriven": true,
        "g3_threePtDriven": false,
        "g4_starInvolved": true,
        "g5_betOnLeader": false,
        "g6_hasCushion": false,
        "g7_earlyGame": true,
        "g8_highProc": false,
        "g9_homeTeam": true,
        "g10_ncaa": true,
        "g11_bigMargin": false,
        "g12_oppCold3": false
      },
      "altGaps": {
        "v1_pureProc": 54,
        "v2_f1low": 63.9,
        "v3_f1high": 67,
        "v4_f3boost": 71,
        "v5_noStar": 52.2
      },
      "v7": {
        "aScq": 0,
        "hScq": 0,
        "aScore": -16.1,
        "hScore": 46.1,
        "gap": 62.2,
        "f5contrib": 0
      },
      "altStructural": {
        "v6_cushionBoost": 62.2,
        "v7_marginWeighted": 6.2,
        "v8_procDiffOnly": 22,
        "v10_timeDecay": 62.2
      },
      "alertSent": true,
      "spreadHistory": [
        {
          "t": "2026-03-08T18:52:28.438Z",
          "spread": -6.5,
          "score": "33-33",
          "period": 1,
          "clock": "1:10"
        },
        {
          "t": "2026-03-08T18:53:32.483Z",
          "spread": -5.5,
          "score": "33-35",
          "period": 1,
          "clock": "1:10"
        },
        {
          "t": "2026-03-08T18:53:32.488Z",
          "spread": -5.5,
          "score": "33-35",
          "period": 1,
          "clock": "1:10"
        },
        {
          "t": "2026-03-08T18:54:37.282Z",
          "spread": -3.5,
          "score": "36-35",
          "period": 1,
          "clock": "0:00"
        },
        {
          "t": "2026-03-08T18:54:37.418Z",
          "spread": -3.5,
          "score": "36-35",
          "period": 1,
          "clock": "0:00"
        },
        {
          "t": "2026-03-08T18:55:41.368Z",
          "spread": -4.5,
          "score": "36-35",
          "period": 1,
          "clock": "0:00"
        },
        {
          "t": "2026-03-08T18:55:41.885Z",
          "spread": -4.5,
          "score": "36-35",
          "period": 1,
          "clock": "0:00"
        },
        {
          "t": "2026-03-08T18:56:45.499Z",
          "spread": -4.5,
          "score": "36-35",
          "period": 1,
          "clock": "0:00"
        },
        {
          "t": "2026-03-08T18:56:45.510Z",
          "spread": -4.5,
          "score": "36-35",
          "period": 1,
          "clock": "0:00"
        },
        {
          "t": "2026-03-08T18:57:50.451Z",
          "spread": -4.5,
          "score": "36-35",
          "period": 1,
          "clock": "0:00"
        },
        {
          "t": "2026-03-08T18:57:50.465Z",
          "spread": -4.5,
          "score": "36-35",
          "period": 1,
          "clock": "0:00"
        },
        {
          "t": "2026-03-08T18:58:56.229Z",
          "spread": -4.5,
          "score": "36-35",
          "period": 1,
          "clock": "0:00"
        },
        {
          "t": "2026-03-08T19:00:01.717Z",
          "spread": -4.5,
          "score": "36-35",
          "period": 1,
          "clock": "0:00"
        },
        {
          "t": "2026-03-08T19:00:01.778Z",
          "spread": -4.5,
          "score": "36-35",
          "period": 1,
          "clock": "0:00"
        },
        {
          "t": "2026-03-08T19:01:05.881Z",
          "spread": -4.5,
          "score": "36-35",
          "period": 1,
          "clock": "0:00"
        },
        {
          "t": "2026-03-08T19:01:05.908Z",
          "spread": -4.5,
          "score": "36-35",
          "period": 1,
          "clock": "0:00"
        },
        {
          "t": "2026-03-08T19:02:10.368Z",
          "spread": -4.5,
          "score": "36-35",
          "period": 1,
          "clock": "0:00"
        },
        {
          "t": "2026-03-08T19:02:10.517Z",
          "spread": -4.5,
          "score": "36-35",
          "period": 1,
          "clock": "0:00"
        },
        {
          "t": "2026-03-08T19:03:16.915Z",
          "spread": -4.5,
          "score": "36-35",
          "period": 1,
          "clock": "0:00"
        },
        {
          "t": "2026-03-08T19:03:16.931Z",
          "spread": -4.5,
          "score": "36-35",
          "period": 1,
          "clock": "0:00"
        },
        {
          "t": "2026-03-08T19:04:20.650Z",
          "spread": -4.5,
          "score": "36-35",
          "period": 1,
          "clock": "0:00"
        },
        {
          "t": "2026-03-08T19:05:24.304Z",
          "spread": -4.5,
          "score": "36-35",
          "period": 1,
          "clock": "0:00"
        },
        {
          "t": "2026-03-08T19:06:28.136Z",
          "spread": -4.5,
          "score": "36-35",
          "period": 1,
          "clock": "0:00"
        },
        {
          "t": "2026-03-08T19:07:32.093Z",
          "spread": -4.5,
          "score": "36-35",
          "period": 1,
          "clock": "0:00"
        },
        {
          "t": "2026-03-08T19:07:32.100Z",
          "spread": -4.5,
          "score": "36-35",
          "period": 1,
          "clock": "0:00"
        },
        {
          "t": "2026-03-08T19:08:35.882Z",
          "spread": -4.5,
          "score": "36-35",
          "period": 1,
          "clock": "0:00"
        },
        {
          "t": "2026-03-08T19:08:36.010Z",
          "spread": -4.5,
          "score": "36-35",
          "period": 1,
          "clock": "0:00"
        },
        {
          "t": "2026-03-08T19:09:40.275Z",
          "spread": -4.5,
          "score": "36-35",
          "period": 1,
          "clock": "0:00"
        },
        {
          "t": "2026-03-08T19:09:40.499Z",
          "spread": -4.5,
          "score": "36-35",
          "period": 1,
          "clock": "0:00"
        },
        {
          "t": "2026-03-08T19:10:44.720Z",
          "spread": -4.5,
          "score": "36-35",
          "period": 1,
          "clock": "0:00"
        },
        {
          "t": "2026-03-08T19:10:45.063Z",
          "spread": -4.5,
          "score": "36-35",
          "period": 1,
          "clock": "0:00"
        },
        {
          "t": "2026-03-08T19:11:48.346Z",
          "spread": -4.5,
          "score": "36-35",
          "period": 1,
          "clock": "0:00"
        },
        {
          "t": "2026-03-08T19:11:48.990Z",
          "spread": -4.5,
          "score": "36-35",
          "period": 1,
          "clock": "0:00"
        }
      ]
    },
    {
      "id": 1772995948466,
      "key": "401851251_sust_CARK",
      "gameId": "401851251",
      "team": "CARK",
      "opponent": "QUC",
      "matchup": "QUC @ CARK",
      "side": "SPREAD",
      "spread": -3.5,
      "signals": [
        "sust"
      ],
      "marketOdds": -114,
      "impliedP": 53.3,
      "estimatedP": 55,
      "kellyPct": 2.5,
      "kellyBet": 500,
      "book": "FanDuel",
      "timestamp": "2026-03-08T18:52:28.466Z",
      "outcome": null,
      "payout": null,
      "mode": "ncaab",
      "awayTeam": "QUC",
      "homeTeam": "CARK",
      "awayName": "Queens University Royals",
      "homeName": "Central Arkansas Bears",
      "awayScore": 30,
      "homeScore": 34,
      "period": 1,
      "clock": "0:00",
      "periodLabel": "H1",
      "sustLeader": "CARK",
      "sustMargin": 4,
      "betOnLeader": true,
      "currentMargin": 4,
      "cushion": 0.5,
      "sustScore": 41.6,
      "fragScore": -27.2,
      "sustGap": 68.8,
      "sustSignals": [
        "Strong process (7.2/10)"
      ],
      "fragSignals": [
        "3PT heavy (60% of pts)"
      ],
      "sustStats": {
        "fg": "43",
        "efg": "52",
        "threePt": "33",
        "twoPt": "47",
        "proc": 7.2,
        "star": 79,
        "scq": 0
      },
      "fragStats": {
        "fg": "38",
        "efg": "50",
        "threePt": "35",
        "twoPt": "27",
        "proc": 4,
        "star": 0,
        "scq": 0
      },
      "sustDetail": "CARK +41.6 vs QUC -27.2 (gap:68.8) | QUC 30-34 CARK | H1 0:00 | FanDuel -3.5 (-114)",
      "strategies": {
        "g1_bigGap": true,
        "g2_procDriven": true,
        "g3_threePtDriven": false,
        "g4_starInvolved": true,
        "g5_betOnLeader": true,
        "g6_hasCushion": true,
        "g7_earlyGame": false,
        "g8_highProc": true,
        "g9_homeTeam": true,
        "g10_ncaa": true,
        "g11_bigMargin": false,
        "g12_oppCold3": false
      },
      "altGaps": {
        "v1_pureProc": 64,
        "v2_f1low": 73.6,
        "v3_f1high": 63.9,
        "v4_f3boost": 81.6,
        "v5_noStar": 68.8
      },
      "v7": {
        "aScq": 0,
        "hScq": 0,
        "aScore": -27.2,
        "hScore": 41.6,
        "gap": 68.8,
        "f5contrib": 0
      },
      "altStructural": {
        "v6_cushionBoost": 70.3,
        "v7_marginWeighted": 27.5,
        "v8_procDiffOnly": 32,
        "v10_timeDecay": 68.8
      },
      "alertSent": true,
      "spreadHistory": [
        {
          "t": "2026-03-08T18:53:32.483Z",
          "spread": -3.5,
          "score": "30-34",
          "period": 1,
          "clock": "0:00"
        },
        {
          "t": "2026-03-08T18:53:32.488Z",
          "spread": -3.5,
          "score": "30-34",
          "period": 1,
          "clock": "0:00"
        },
        {
          "t": "2026-03-08T18:54:37.282Z",
          "spread": -3.5,
          "score": "30-34",
          "period": 1,
          "clock": "0:00"
        },
        {
          "t": "2026-03-08T18:54:37.418Z",
          "spread": -3.5,
          "score": "30-34",
          "period": 1,
          "clock": "0:00"
        },
        {
          "t": "2026-03-08T18:55:41.368Z",
          "spread": -3.5,
          "score": "30-34",
          "period": 1,
          "clock": "0:00"
        },
        {
          "t": "2026-03-08T18:55:41.885Z",
          "spread": -3.5,
          "score": "30-34",
          "period": 1,
          "clock": "0:00"
        },
        {
          "t": "2026-03-08T18:56:45.499Z",
          "spread": -3.5,
          "score": "30-34",
          "period": 1,
          "clock": "0:00"
        },
        {
          "t": "2026-03-08T18:56:45.511Z",
          "spread": -3.5,
          "score": "30-34",
          "period": 1,
          "clock": "0:00"
        },
        {
          "t": "2026-03-08T18:57:50.452Z",
          "spread": -3.5,
          "score": "30-34",
          "period": 1,
          "clock": "0:00"
        },
        {
          "t": "2026-03-08T18:57:50.466Z",
          "spread": -3.5,
          "score": "30-34",
          "period": 1,
          "clock": "0:00"
        },
        {
          "t": "2026-03-08T18:58:56.229Z",
          "spread": -3.5,
          "score": "30-34",
          "period": 1,
          "clock": "0:00"
        },
        {
          "t": "2026-03-08T19:00:01.717Z",
          "spread": -3.5,
          "score": "30-34",
          "period": 1,
          "clock": "0:00"
        },
        {
          "t": "2026-03-08T19:00:01.779Z",
          "spread": -3.5,
          "score": "30-34",
          "period": 1,
          "clock": "0:00"
        },
        {
          "t": "2026-03-08T19:01:05.882Z",
          "spread": -3.5,
          "score": "30-34",
          "period": 1,
          "clock": "0:00"
        },
        {
          "t": "2026-03-08T19:01:05.908Z",
          "spread": -3.5,
          "score": "30-34",
          "period": 1,
          "clock": "0:00"
        },
        {
          "t": "2026-03-08T19:02:10.369Z",
          "spread": -3.5,
          "score": "30-34",
          "period": 1,
          "clock": "0:00"
        },
        {
          "t": "2026-03-08T19:02:10.517Z",
          "spread": -3.5,
          "score": "30-34",
          "period": 1,
          "clock": "0:00"
        },
        {
          "t": "2026-03-08T19:03:16.918Z",
          "spread": -3.5,
          "score": "30-34",
          "period": 1,
          "clock": "0:00"
        },
        {
          "t": "2026-03-08T19:03:16.933Z",
          "spread": -3.5,
          "score": "30-34",
          "period": 1,
          "clock": "0:00"
        },
        {
          "t": "2026-03-08T19:04:20.651Z",
          "spread": -3.5,
          "score": "30-34",
          "period": 1,
          "clock": "0:00"
        },
        {
          "t": "2026-03-08T19:05:24.304Z",
          "spread": -3.5,
          "score": "30-34",
          "period": 1,
          "clock": "0:00"
        },
        {
          "t": "2026-03-08T19:06:28.136Z",
          "spread": -3.5,
          "score": "30-34",
          "period": 1,
          "clock": "0:00"
        },
        {
          "t": "2026-03-08T19:07:32.094Z",
          "spread": -3.5,
          "score": "30-34",
          "period": 1,
          "clock": "0:00"
        },
        {
          "t": "2026-03-08T19:07:32.100Z",
          "spread": -3.5,
          "score": "30-34",
          "period": 1,
          "clock": "0:00"
        },
        {
          "t": "2026-03-08T19:08:35.882Z",
          "spread": -3.5,
          "score": "30-34",
          "period": 1,
          "clock": "0:00"
        },
        {
          "t": "2026-03-08T19:08:36.011Z",
          "spread": -3.5,
          "score": "30-34",
          "period": 1,
          "clock": "0:00"
        },
        {
          "t": "2026-03-08T19:09:40.275Z",
          "spread": -2.5,
          "score": "35-37",
          "period": 2,
          "clock": "18:38"
        },
        {
          "t": "2026-03-08T19:09:40.499Z",
          "spread": -2.5,
          "score": "35-37",
          "period": 2,
          "clock": "18:38"
        },
        {
          "t": "2026-03-08T19:10:44.721Z",
          "spread": -2.5,
          "score": "35-37",
          "period": 2,
          "clock": "18:33"
        },
        {
          "t": "2026-03-08T19:10:45.063Z",
          "spread": -2.5,
          "score": "35-37",
          "period": 2,
          "clock": "18:33"
        },
        {
          "t": "2026-03-08T19:11:48.346Z",
          "spread": -2.5,
          "score": "35-37",
          "period": 2,
          "clock": "18:33"
        },
        {
          "t": "2026-03-08T19:11:48.992Z",
          "spread": -2.5,
          "score": "35-37",
          "period": 2,
          "clock": "18:33"
        }
      ]
    },
    {
      "id": 1772995948704,
      "key": "401828264_sust_TULN",
      "gameId": "401828264",
      "team": "TULN",
      "opponent": "MEM",
      "matchup": "MEM @ TULN",
      "side": "SPREAD",
      "spread": -4.5,
      "signals": [
        "sust"
      ],
      "marketOdds": -118,
      "impliedP": 54.1,
      "estimatedP": 55,
      "kellyPct": 2.5,
      "kellyBet": 500,
      "book": "FanDuel",
      "timestamp": "2026-03-08T18:52:28.704Z",
      "outcome": null,
      "payout": null,
      "mode": "ncaab",
      "awayTeam": "MEM",
      "homeTeam": "TULN",
      "awayName": "Memphis Tigers",
      "homeName": "Tulane Green Wave",
      "awayScore": 27,
      "homeScore": 35,
      "period": 1,
      "clock": "2:08",
      "periodLabel": "H1",
      "sustLeader": "TULN",
      "sustMargin": 6,
      "betOnLeader": true,
      "currentMargin": 6,
      "cushion": 3.5,
      "sustScore": 39.1,
      "fragScore": 4.1,
      "sustGap": 35,
      "sustSignals": [
        "Low 3PT reliance (27%)"
      ],
      "fragSignals": [],
      "sustStats": {
        "fg": "48",
        "efg": "54",
        "threePt": "27",
        "twoPt": "55",
        "proc": 6.7,
        "star": 102,
        "scq": 0
      },
      "fragStats": {
        "fg": "36",
        "efg": "41",
        "threePt": "22",
        "twoPt": "44",
        "proc": 5.1,
        "star": 0,
        "scq": 0
      },
      "sustDetail": "TULN +36.6 vs MEM 6.1 (gap:30.5) | MEM 27-33 TULN | H1 2:36 | FanDuel -3.5 (-118)",
      "strategies": {
        "g1_bigGap": false,
        "g2_procDriven": true,
        "g3_threePtDriven": false,
        "g4_starInvolved": true,
        "g5_betOnLeader": true,
        "g6_hasCushion": true,
        "g7_earlyGame": true,
        "g8_highProc": false,
        "g9_homeTeam": true,
        "g10_ncaa": true,
        "g11_bigMargin": false,
        "g12_oppCold3": true
      },
      "altGaps": {
        "v1_pureProc": 32,
        "v2_f1low": 34.2,
        "v3_f1high": 21.6,
        "v4_f3boost": 36.9,
        "v5_noStar": 30.5
      },
      "v7": {
        "aScq": 0,
        "hScq": 0,
        "aScore": 6.1,
        "hScore": 36.6,
        "gap": 30.5,
        "f5contrib": 0
      },
      "altStructural": {
        "v6_cushionBoost": 38,
        "v7_marginWeighted": 18.3,
        "v8_procDiffOnly": 16,
        "v10_timeDecay": 30.5
      },
      "spreadHistory": [
        {
          "t": "2026-03-08T18:53:32.483Z",
          "spread": -4.5,
          "score": "27-35",
          "period": 1,
          "clock": "2:08"
        },
        {
          "t": "2026-03-08T18:53:32.488Z",
          "spread": -4.5,
          "score": "27-35",
          "period": 1,
          "clock": "2:08"
        },
        {
          "t": "2026-03-08T18:54:37.283Z",
          "spread": -4.5,
          "score": "29-40",
          "period": 1,
          "clock": "1:02"
        },
        {
          "t": "2026-03-08T18:54:37.418Z",
          "spread": -4.5,
          "score": "29-40",
          "period": 1,
          "clock": "1:02"
        },
        {
          "t": "2026-03-08T18:55:41.368Z",
          "spread": -6.5,
          "score": "29-40",
          "period": 1,
          "clock": "0:46"
        },
        {
          "t": "2026-03-08T18:55:41.886Z",
          "spread": -6.5,
          "score": "29-40",
          "period": 1,
          "clock": "0:46"
        },
        {
          "t": "2026-03-08T18:56:45.500Z",
          "spread": -6.5,
          "score": "31-40",
          "period": 1,
          "clock": "0:32"
        },
        {
          "t": "2026-03-08T18:56:45.511Z",
          "spread": -6.5,
          "score": "31-40",
          "period": 1,
          "clock": "0:32"
        },
        {
          "t": "2026-03-08T18:57:50.452Z",
          "spread": -6.5,
          "score": "31-40",
          "period": 1,
          "clock": "0:32"
        },
        {
          "t": "2026-03-08T18:57:50.466Z",
          "spread": -6.5,
          "score": "31-40",
          "period": 1,
          "clock": "0:32"
        },
        {
          "t": "2026-03-08T18:58:56.229Z",
          "spread": -6.5,
          "score": "31-40",
          "period": 1,
          "clock": "0:03"
        },
        {
          "t": "2026-03-08T19:00:01.718Z",
          "spread": -5.5,
          "score": "31-40",
          "period": 1,
          "clock": "0:03"
        },
        {
          "t": "2026-03-08T19:00:01.779Z",
          "spread": -5.5,
          "score": "31-40",
          "period": 1,
          "clock": "0:03"
        },
        {
          "t": "2026-03-08T19:01:05.882Z",
          "spread": -5.5,
          "score": "31-40",
          "period": 1,
          "clock": "0:00"
        },
        {
          "t": "2026-03-08T19:01:05.908Z",
          "spread": -5.5,
          "score": "31-40",
          "period": 1,
          "clock": "0:00"
        },
        {
          "t": "2026-03-08T19:02:10.369Z",
          "spread": -5.5,
          "score": "31-40",
          "period": 1,
          "clock": "0:00"
        },
        {
          "t": "2026-03-08T19:02:10.519Z",
          "spread": -5.5,
          "score": "31-40",
          "period": 1,
          "clock": "0:00"
        },
        {
          "t": "2026-03-08T19:03:16.918Z",
          "spread": -5.5,
          "score": "31-40",
          "period": 1,
          "clock": "0:00"
        },
        {
          "t": "2026-03-08T19:03:16.934Z",
          "spread": -5.5,
          "score": "31-40",
          "period": 1,
          "clock": "0:00"
        },
        {
          "t": "2026-03-08T19:04:20.651Z",
          "spread": -5.5,
          "score": "31-40",
          "period": 1,
          "clock": "0:00"
        },
        {
          "t": "2026-03-08T19:05:24.304Z",
          "spread": -5.5,
          "score": "31-40",
          "period": 1,
          "clock": "0:00"
        },
        {
          "t": "2026-03-08T19:06:28.137Z",
          "spread": -5.5,
          "score": "31-40",
          "period": 1,
          "clock": "0:00"
        },
        {
          "t": "2026-03-08T19:07:32.095Z",
          "spread": -5.5,
          "score": "31-40",
          "period": 1,
          "clock": "0:00"
        },
        {
          "t": "2026-03-08T19:07:32.102Z",
          "spread": -5.5,
          "score": "31-40",
          "period": 1,
          "clock": "0:00"
        },
        {
          "t": "2026-03-08T19:08:35.882Z",
          "spread": -5.5,
          "score": "31-40",
          "period": 1,
          "clock": "0:00"
        },
        {
          "t": "2026-03-08T19:08:36.011Z",
          "spread": -5.5,
          "score": "31-40",
          "period": 1,
          "clock": "0:00"
        },
        {
          "t": "2026-03-08T19:09:40.277Z",
          "spread": -5.5,
          "score": "31-40",
          "period": 1,
          "clock": "0:00"
        },
        {
          "t": "2026-03-08T19:09:40.502Z",
          "spread": -5.5,
          "score": "31-40",
          "period": 1,
          "clock": "0:00"
        },
        {
          "t": "2026-03-08T19:10:44.721Z",
          "spread": -5.5,
          "score": "31-40",
          "period": 1,
          "clock": "0:00"
        },
        {
          "t": "2026-03-08T19:10:45.063Z",
          "spread": -5.5,
          "score": "31-40",
          "period": 1,
          "clock": "0:00"
        },
        {
          "t": "2026-03-08T19:11:48.348Z",
          "spread": -5.5,
          "score": "31-40",
          "period": 1,
          "clock": "0:00"
        },
        {
          "t": "2026-03-08T19:11:48.993Z",
          "spread": -5.5,
          "score": "31-40",
          "period": 1,
          "clock": "0:00"
        }
      ],
      "alertSent": true
    },
    {
      "id": 1772997109680,
      "key": "401828263_sust_USF",
      "gameId": "401828263",
      "team": "USF",
      "opponent": "CLT",
      "matchup": "CLT @ USF",
      "side": "SPREAD",
      "spread": -21.5,
      "signals": [
        "sust"
      ],
      "marketOdds": -118,
      "impliedP": 54.1,
      "estimatedP": 55,
      "kellyPct": 2.5,
      "kellyBet": 500,
      "book": "FanDuel",
      "timestamp": "2026-03-08T19:11:49.680Z",
      "outcome": null,
      "payout": null,
      "mode": "ncaab",
      "awayTeam": "CLT",
      "homeTeam": "USF",
      "awayName": "Charlotte 49ers",
      "homeName": "South Florida Bulls",
      "awayScore": 29,
      "homeScore": 44,
      "period": 2,
      "clock": "19:16",
      "periodLabel": "H2",
      "sustLeader": "USF",
      "sustMargin": 15,
      "betOnLeader": true,
      "currentMargin": 15,
      "cushion": -6.5,
      "sustScore": 32.5,
      "fragScore": -7.6,
      "sustGap": 40.1,
      "sustSignals": [],
      "fragSignals": [],
      "sustStats": {
        "fg": "42",
        "efg": "51",
        "threePt": "44",
        "twoPt": "41",
        "proc": 6.8,
        "star": 142,
        "scq": 0
      },
      "fragStats": {
        "fg": "46",
        "efg": "54",
        "threePt": "36",
        "twoPt": "48",
        "proc": 4.7,
        "star": 0,
        "scq": 0
      },
      "sustDetail": "USF +32.5 vs CLT -7.6 (gap:40.1) | CLT 29-44 USF | H2 19:16 | FanDuel -21.5 (-118)",
      "strategies": {
        "g1_bigGap": false,
        "g2_procDriven": true,
        "g3_threePtDriven": false,
        "g4_starInvolved": true,
        "g5_betOnLeader": true,
        "g6_hasCushion": false,
        "g7_earlyGame": false,
        "g8_highProc": false,
        "g9_homeTeam": true,
        "g10_ncaa": true,
        "g11_bigMargin": true,
        "g12_oppCold3": false
      },
      "altGaps": {
        "v1_pureProc": 42,
        "v2_f1low": 44.9,
        "v3_f1high": 28.5,
        "v4_f3boost": 48.5,
        "v5_noStar": 40.1
      },
      "v7": {
        "aScq": 0,
        "hScq": 0,
        "aScore": -7.6,
        "hScore": 32.5,
        "gap": 40.1,
        "f5contrib": 0
      },
      "altStructural": {
        "v6_cushionBoost": 40.1,
        "v7_marginWeighted": 60.2,
        "v8_procDiffOnly": 21,
        "v10_timeDecay": 40.1
      },
      "alertSent": true
    }
  ],
  "resolved": []
}